multipleloader/LoaderError.py
multipleloader/__init__.py
multipleloader/extension_settings.py
multipleloader/multipleloader.py
multipleloader/loader/csv_loader.py
multipleloader/loader/joblib_loader.py
multipleloader/loader/json_loader.py
multipleloader/loader/numpy_loader.py
multipleloader/loader/pandas_loader.py
multipleloader/loader/pickle_loader.py
multipleloader/loader/loading_src/file_main_loader_class.py
multipleloader-1.0.2.dist-info/LICENSE
multipleloader-1.0.2.dist-info/METADATA
multipleloader-1.0.2.dist-info/WHEEL
multipleloader-1.0.2.dist-info/top_level.txt
multipleloader-1.0.2.dist-info/RECORD
