Metadata-Version: 2.1
Name: multipleloader
Version: 1.0.2
Summary: Automatic loading of files with any extension
Home-page: https://github.com/Domzou-kun/multiple_loader
Download-URL: https://github.com/Domzou-kun/multiple_loader
Author: Domzou
License: MIT
Keywords: Python python multi file folder directory loader save loading load reader
Classifier: Operating System :: Microsoft :: Windows :: Windows 10
Classifier: Programming Language :: Python :: 3.8
Classifier: Programming Language :: Python :: 3.9
Classifier: Programming Language :: Python :: 3.10
Classifier: Topic :: Software Development :: Libraries :: Python Modules
License-File: LICENSE
Requires-Dist: numpy
Requires-Dist: pandas
Requires-Dist: joblib
